abs_imports.py
abs_imports-0.2.1.dist-info/LICENSE
abs_imports-0.2.1.dist-info/METADATA
abs_imports-0.2.1.dist-info/WHEEL
abs_imports-0.2.1.dist-info/entry_points.txt
abs_imports-0.2.1.dist-info/top_level.txt
abs_imports-0.2.1.dist-info/RECORD
